tournament/__init__.py
tournament/__main__.py
tournament/config.py
tournament/matchmaker.py
tournament/queue.py
tournament/redis.py
tournament/server.py
tournament-1.0.0.dist-info/LICENSE
tournament-1.0.0.dist-info/METADATA
tournament-1.0.0.dist-info/WHEEL
tournament-1.0.0.dist-info/entry_points.txt
tournament-1.0.0.dist-info/top_level.txt
tournament-1.0.0.dist-info/RECORD
